PD_loss_balancing/__init__.py
PD_loss_balancing/main.py
pd_loss_balancing-0.2.1.dist-info/METADATA
pd_loss_balancing-0.2.1.dist-info/WHEEL
pd_loss_balancing-0.2.1.dist-info/top_level.txt
pd_loss_balancing-0.2.1.dist-info/RECORD
