Metadata-Version: 2.4
Name: PD_loss_balancing
Version: 0.2.1
Summary: A package for stabalizing and controllolling loss with feedback control
Author: Addie Foote
Author-email: addiefoote8@gmail.com
Classifier: Programming Language :: Python :: 3
Classifier: License :: OSI Approved :: MIT License
Classifier: Operating System :: OS Independent
Requires-Python: >=3.6
Requires-Dist: torch
Requires-Dist: numpy
Requires-Dist: wandb
Dynamic: author
Dynamic: author-email
Dynamic: classifier
Dynamic: description
Dynamic: description-content-type
Dynamic: requires-dist
Dynamic: requires-python
Dynamic: summary
